AUTHORS
LICENSE
MANIFEST.in
README.md
TODO
pyproject.toml
setup.py
debmutate/__init__.py
debmutate/_deb822.py
debmutate/_rules.py
debmutate/ben.py
debmutate/changelog.py
debmutate/control.py
debmutate/copyright.py
debmutate/deb822.py
debmutate/debcargo.py
debmutate/debhelper.py
debmutate/lintian_overrides.py
debmutate/orig.py
debmutate/patch.py
debmutate/py.typed
debmutate/reformatting.py
debmutate/vcs.py
debmutate/vendor.py
debmutate/versions.py
debmutate/watch.py
debmutate.egg-info/PKG-INFO
debmutate.egg-info/SOURCES.txt
debmutate.egg-info/dependency_links.txt
debmutate.egg-info/requires.txt
debmutate.egg-info/top_level.txt
scripts/deb-enable-rrr
scripts/drop-mia-uploaders
tests/__init__.py
tests/test__rules.py
tests/test_changelog.py
tests/test_control.py
tests/test_copyright.py
tests/test_deb822.py
tests/test_debcargo.py
tests/test_debhelper.py
tests/test_debmutate.py
tests/test_lintian_overrides.py
tests/test_orig.py
tests/test_patch.py
tests/test_reformatting.py
tests/test_vcs.py
tests/test_versions.py
tests/test_watch.py