Metadata-Version: 2.1
Name: debmutate
Version: 0.69
Summary: manipulation of Debian package control files
Author-email: Jelmer Vernooĳ <jelmer@debian.org>
Project-URL: Homepage, https://salsa.debian.org/jelmer/debmutate
Project-URL: Repository, https://salsa.debian.org/jelmer/debmutate.git
Requires-Python: >=3.8
License-File: LICENSE
License-File: AUTHORS
Requires-Dist: python_debian>=0.1.44
Requires-Dist: python-tr
Requires-Dist: merge3
Provides-Extra: debcargo
Requires-Dist: tomlkit; extra == "debcargo"
Provides-Extra: watch
Requires-Dist: pcre2; extra == "watch"
